MANIFEST.in
README.rst
setup.py
version.txt
rhaptos2.common.egg-info/PKG-INFO
rhaptos2.common.egg-info/SOURCES.txt
rhaptos2.common.egg-info/dependency_links.txt
rhaptos2.common.egg-info/namespace_packages.txt
rhaptos2.common.egg-info/requires.txt
rhaptos2.common.egg-info/top_level.txt
rhaptos2/common/__init__.py
rhaptos2/common/conf.py
rhaptos2/common/conf_definitions.py
rhaptos2/common/err.py
rhaptos2/common/log.py