Metadata-Version: 1.0
Name: rhaptos2.common
Version: 0.0.18
Summary: Common libraries for Rhaptos2
Home-page: https://github.com/Connexions/rhaptos2.common
Author: See AUTHORS.txt
Author-email: info@cnx.org
License: LICENSE.txt
Platform: UNKNOWN
